machine_learning/__init__.py
Auto_ML_study-0.0.2.dist-info/LICENSE
Auto_ML_study-0.0.2.dist-info/METADATA
Auto_ML_study-0.0.2.dist-info/WHEEL
Auto_ML_study-0.0.2.dist-info/top_level.txt
Auto_ML_study-0.0.2.dist-info/RECORD
